LICENSE
MANIFEST.in
README.rst
setup.py
django_model_blocks.egg-info/PKG-INFO
django_model_blocks.egg-info/SOURCES.txt
django_model_blocks.egg-info/dependency_links.txt
django_model_blocks.egg-info/not-zip-safe
django_model_blocks.egg-info/requires.txt
django_model_blocks.egg-info/top_level.txt
model_blocks/__init__.py
model_blocks/models.py
model_blocks/tests.py
model_blocks/views.py
model_blocks/static/model_blocks/simple.css
model_blocks/templates/model_blocks/object_detail.html
model_blocks/templates/model_blocks/object_list.html
model_blocks/templates/model_blocks/object_teaser.html
model_blocks/templatetags/__init__.py
model_blocks/templatetags/model_blocks.py
model_blocks/templatetags/model_filters.py
model_blocks/templatetags/model_nodes.py
model_blocks/templatetags/model_tags.py