Metadata-Version: 1.1
Name: django-model-blocks
Version: 0.8.10
Summary: Simple filters and tags for generic Django model template partials
Home-page: https://github.com/mjumbewu/django-model-blocks/
Author: Mjumbe Wawatu Ukweli
Author-email: mjumbewu@kwawatu.com
License: UNKNOWN
Download-URL: https://github.com/mjumbewu/django-model-blocks/downloads
Platform: UNKNOWN
Classifier: Development Status :: 4 - Beta
Classifier: Environment :: Web Environment
Classifier: Framework :: Django
Classifier: Intended Audience :: Developers
Classifier: License :: OSI Approved :: BSD License
Classifier: Operating System :: OS Independent
Classifier: Programming Language :: Python
Classifier: Topic :: Utilities
Provides: model_blocks
Obsoletes: model_filters
